zeromcp/__init__.py
zeromcp/jsonrpc.py
zeromcp/mcp.py
zeromcp/py.typed
zeromcp-1.2.0.dist-info/METADATA
zeromcp-1.2.0.dist-info/WHEEL
zeromcp-1.2.0.dist-info/licenses/LICENSE
zeromcp-1.2.0.dist-info/RECORD
