Metadata-Version: 2.4
Name: zeromcp
Version: 1.2.0
Summary: Zero-dependency MCP server implementation
Project-URL: Homepage, https://github.com/mrexodia/zeromcp
Project-URL: Repository, https://github.com/mrexodia/zeromcp
Project-URL: Issues, https://github.com/mrexodia/zeromcp/issues
License-Expression: MIT
License-File: LICENSE
Requires-Python: >=3.11
